<?xml version="1.0" encoding="utf-8" ?>
<dwsync>
<file name="constants.js" server="s9-chicago.accountservergroup.com/public_html/" local="131642675732114997" remote="131642787000000000" Dst="1" />
<file name="glossarylist.js" server="s9-chicago.accountservergroup.com/public_html/" local="129858646960000000" remote="131642787000000000" Dst="1" />
<file name="glossarylistloader.js" server="s9-chicago.accountservergroup.com/public_html/" local="131642675759559142" remote="131642787000000000" Dst="1" />
<file name="indextree.js" server="s9-chicago.accountservergroup.com/public_html/" local="129858646960000000" remote="131642787000000000" Dst="1" />
<file name="indextreeloader.js" server="s9-chicago.accountservergroup.com/public_html/" local="131642675760782326" remote="131642787000000000" Dst="1" />
<file name="loadcsh.js" server="s9-chicago.accountservergroup.com/public_html/" local="131642675733368342" remote="131642787000000000" Dst="1" />
<file name="loadparentdata.js" server="s9-chicago.accountservergroup.com/public_html/" local="131642675733498677" remote="131642787000000000" Dst="1" />
<file name="loadprojdata.js" server="s9-chicago.accountservergroup.com/public_html/" local="131642675733649086" remote="131642787000000000" Dst="1" />
<file name="loadscreen.js" server="s9-chicago.accountservergroup.com/public_html/" local="131642675733208123" remote="131642787000000000" Dst="1" />
<file name="mhlang.js" server="s9-chicago.accountservergroup.com/public_html/" local="131642675732706579" remote="131642787000000000" Dst="1" />
<file name="mhfhost.js" server="s9-chicago.accountservergroup.com/public_html/" local="131642675762025488" remote="131642787000000000" Dst="1" />
<file name="mhtopic.js" server="s9-chicago.accountservergroup.com/public_html/" local="131642675734320974" remote="131642787000000000" Dst="1" />
<file name="mhutils.js" server="s9-chicago.accountservergroup.com/public_html/" local="131642675732556324" remote="131642787000000000" Dst="1" />
<file name="mhver.js" server="s9-chicago.accountservergroup.com/public_html/" local="131642675732836911" remote="131642787000000000" Dst="1" />
<file name="pageloader.js" server="s9-chicago.accountservergroup.com/public_html/" local="131642675733879846" remote="131642787000000000" Dst="1" />
<file name="search.js" server="s9-chicago.accountservergroup.com/public_html/" local="131642675762172757" remote="131642787000000000" Dst="1" />
<file name="searchfield.js" server="s9-chicago.accountservergroup.com/public_html/" local="131642675734481289" remote="131642787000000000" Dst="1" />
<file name="settings.js" server="s9-chicago.accountservergroup.com/public_html/" local="129858646960000000" remote="131642787000000000" Dst="1" />
<file name="showhidecontrols.js" server="s9-chicago.accountservergroup.com/public_html/" local="131642675733779438" remote="131642787000000000" Dst="1" />
<file name="tocdrilldown.js" server="s9-chicago.accountservergroup.com/public_html/" local="129858646980000000" remote="131642787000000000" Dst="1" />
<file name="tocdrilldownloader.js" server="s9-chicago.accountservergroup.com/public_html/" local="131642675762954833" remote="131642787000000000" Dst="1" />
<file name="utils.js" server="s9-chicago.accountservergroup.com/public_html/" local="131642675732335581" remote="131642787000000000" Dst="1" />
<file name="XmlJsReader.js" server="s9-chicago.accountservergroup.com/public_html/" local="131642675733057516" remote="131642787000000000" Dst="1" />
</dwsync>